flake8_alphabetize/__init__.py
flake8_alphabetize/core.py
flake8_alphabetize-0.0.21.dist-info/LICENSE
flake8_alphabetize-0.0.21.dist-info/METADATA
flake8_alphabetize-0.0.21.dist-info/WHEEL
flake8_alphabetize-0.0.21.dist-info/entry_points.txt
flake8_alphabetize-0.0.21.dist-info/top_level.txt
flake8_alphabetize-0.0.21.dist-info/RECORD
