Metadata-Version: 2.1
Name: flake8-alphabetize
Version: 0.0.21
Summary: A Python style checker for alphabetizing import and __all__.
License: MIT No Attribution
Project-URL: Homepage, https://github.com/tlocke/flake8-alphabetize
Keywords: flake8
Classifier: Framework :: Flake8
Classifier: Environment :: Console
Classifier: Intended Audience :: Developers
Classifier: License :: OSI Approved :: MIT No Attribution License (MIT-0)
Classifier: Programming Language :: Python
Classifier: Programming Language :: Python :: 3
Classifier: Programming Language :: Python :: 3.7
Classifier: Programming Language :: Python :: 3.8
Classifier: Programming Language :: Python :: 3.9
Classifier: Programming Language :: Python :: 3.10
Classifier: Topic :: Software Development :: Libraries :: Python Modules
Classifier: Topic :: Software Development :: Quality Assurance
Requires-Python: >=3.7
License-File: LICENSE
Requires-Dist: flake8 (>3.0.0)
Requires-Dist: stdlib-list (==0.8.0) ; python_version < "3.10"
Requires-Dist: importlib-metadata (>=1.0) ; python_version < "3.8"
